crew_agents/__init__.py
crew_agents/__main__.py
crew_agents/crew.py
crew_agents/main.py
crew_agents/run_flow.py
crew_agents/base/__init__.py
crew_agents/base/archetypes.yaml
crew_agents/config/__init__.py
crew_agents/config/agents.yaml
crew_agents/config/llm.py
crew_agents/config/tasks.yaml
crew_agents/core/__init__.py
crew_agents/core/discovery.py
crew_agents/core/loader.py
crew_agents/core/runner.py
crew_agents/crews/__init__.py
crew_agents/crews/asset_pipeline/__init__.py
crew_agents/crews/asset_pipeline/asset_crew.py
crew_agents/crews/asset_pipeline/config/agents.yaml
crew_agents/crews/asset_pipeline/config/tasks.yaml
crew_agents/crews/creature_design/__init__.py
crew_agents/crews/creature_design/creature_design_crew.py
crew_agents/crews/creature_design/config/agents.yaml
crew_agents/crews/creature_design/config/tasks.yaml
crew_agents/crews/ecs_implementation/__init__.py
crew_agents/crews/ecs_implementation/ecs_crew.py
crew_agents/crews/ecs_implementation/config/agents.yaml
crew_agents/crews/ecs_implementation/config/tasks.yaml
crew_agents/crews/game_builder/__init__.py
crew_agents/crews/game_builder/game_builder_crew.py
crew_agents/crews/game_builder/config/agents.yaml
crew_agents/crews/game_builder/config/tasks.yaml
crew_agents/crews/gameplay_design/__init__.py
crew_agents/crews/gameplay_design/gameplay_design_crew.py
crew_agents/crews/gameplay_design/config/agents.yaml
crew_agents/crews/gameplay_design/config/tasks.yaml
crew_agents/crews/qa_validation/__init__.py
crew_agents/crews/qa_validation/qa_crew.py
crew_agents/crews/qa_validation/config/agents.yaml
crew_agents/crews/qa_validation/config/tasks.yaml
crew_agents/crews/rendering/__init__.py
crew_agents/crews/rendering/rendering_crew.py
crew_agents/crews/rendering/config/agents.yaml
crew_agents/crews/rendering/config/tasks.yaml
crew_agents/crews/world_design/__init__.py
crew_agents/crews/world_design/world_design_crew.py
crew_agents/crews/world_design/config/agents.yaml
agentic_control_crews-0.2.0.dist-info/METADATA
agentic_control_crews-0.2.0.dist-info/WHEEL
agentic_control_crews-0.2.0.dist-info/entry_points.txt
agentic_control_crews-0.2.0.dist-info/RECORD
