Metadata-Version: 2.4
Name: agentic-control-crews
Version: 0.2.0
Summary: CrewAI engine for agentic-control - autonomous AI crews for development tasks
Project-URL: Homepage, https://github.com/jbcom/agentic-control
Project-URL: Repository, https://github.com/jbcom/agentic-control
Project-URL: Documentation, https://github.com/jbcom/agentic-control/tree/main/python#readme
Author-email: Jon Bogaty <jon@jonbogaty.com>
License: MIT
Keywords: ai-agents,automation,crewai,mcp
Classifier: Development Status :: 4 - Beta
Classifier: Intended Audience :: Developers
Classifier: License :: OSI Approved :: MIT License
Classifier: Programming Language :: Python :: 3.11
Classifier: Programming Language :: Python :: 3.12
Classifier: Programming Language :: Python :: 3.13
Requires-Python: >=3.11
Requires-Dist: crewai[anthropic,tools]>=1.5.0
Requires-Dist: pydantic>=2.12.4
Requires-Dist: pyyaml>=6.0.3
Requires-Dist: vendor-connectors[meshy]>=202511.12.0
Provides-Extra: mcp
Requires-Dist: mcp>=1.0.0; extra == 'mcp'
Provides-Extra: tests
Requires-Dist: pytest-cov>=5.0.0; extra == 'tests'
Requires-Dist: pytest-mock>=3.15.1; extra == 'tests'
Requires-Dist: pytest>=9.0.1; extra == 'tests'
